{
    "modelo_educativo": {
        "2": "Internacional",
        "40": "Britanico",
        "46": "Americano",
        "75": "Europeo",
        "141": "Frances",
        "154": "Otros"
    },
    "idioma_de_clases": {
        "3": "Castellano",
        "4": "Ingles",
        "5": "Frances",
        "6": "Alemán",
        "7": "Chino",
        "52": "Otros",
        "105": "Alemán, francés, chino",
        "124": "catalán"
    },
    "cursos_ofrecidos": {
        "8": "Infantil",
        "9": "Primaria",
        "10": "ESO",
        "11": "Bachillerato"
    },
    "curriculum_academico": {
        "12": "International Baccalaureate Diploma Programme (IBDP)",
        "41": "Advanced Level (A-Level)",
        "47": "Bachillerato estadounidense (High School Diploma)",
        "62": "International General Certificate of Secondary Education (IGCSE)",
        "63": "Advanced International Certificate of Education (AICE)",
        "67": "Bachillerato Europeo",
        "78": "Advanced Placement International Diploma (APID)"
    },
    "poblacion": {
        "13": "castelló de la plana",
        "42": "almuñecar",
        "48": "esplugues de llobregat",
        "53": "puçol",
        "56": "alcobendas",
        "58": "paterna",
        "59": "valencia",
        "64": "rocafort",
        "68": "alicante",
        "71": "huércal de almería",
        "73": "espartinas",
        "76": "roquetas de mar",
        "77": "madrid",
        "80": "cuarte de huerva",
        "82": "el palmar",
        "84": "alhaurín de la torre",
        "86": "las rozas",
        "88": "el puerto de santa maría",
        "90": "jaén",
        "92": "san miguel de salinas",
        "95": "benidorm",
        "99": "la garriga",
        "103": "picassent",
        "104": "ojén",
        "106": "pontevedra",
        "108": "santiago de compostela",
        "110": "granada",
        "111": "chamartín",
        "112": "las vaguadas",
        "114": "algeciras",
        "116": "la moraleja",
        "117": "málaga",
        "118": "bellavista-aljaraque",
        "120": "boadilla del monte",
        "121": "villanueva de la cañada",
        "122": "a coruña",
        "125": "barcelona",
        "127": "pozuelo de alarcón",
        "128": "l´eliana",
        "129": "toledo",
        "130": "torrente",
        "131": "soto de viñuelas",
        "134": "sant just desvern",
        "135": "benitachell",
        "136": "moralzarzal",
        "137": "aravaca",
        "138": "elche",
        "140": "san pedro alcántara",
        "142": "campo olivar,godella",
        "143": "el campello",
        "144": "girona",
        "146": "benalmádena",
        "147": "cártama estación",
        "148": "rincón de la victoria",
        "149": "manacor",
        "151": "monforte del cid",
        "152": "el ejido",
        "153": "sotogrande"
    },
    "provincia": {
        "14": "castellón",
        "43": "granada",
        "49": "barcelona",
        "54": "valencia",
        "57": "madrid",
        "69": "alicante",
        "72": "almería",
        "74": "sevilla",
        "81": "zaragoza",
        "83": "murcia",
        "85": "málaga",
        "89": "cádiz",
        "91": "jaén",
        "107": "pontevedra",
        "109": "a coruña",
        "113": "badajoz",
        "115": "algeciras",
        "119": "huelva",
        "123": "galicia",
        "145": "girona",
        "150": "islas baleares"
    },
    "pais": {
        "15": "españa"
    },
    "equipamiento": {
        "16": "Piscina climatizada",
        "17": "Piscina sin climatizar",
        "18": "Campo de futbol",
        "19": "Aire acondicionado",
        "50": "Campo de tenis",
        "51": "Adaptado para personas con minusvalía",
        "55": "Instalaciones olímpicas",
        "93": "Campo de hípica",
        "96": "Edificio individual"
    },
    "servicios_ofrecidos": {
        "20": "Transporte escolar",
        "21": "Seguro de salud o vida",
        "22": "Horario ampliado matutino",
        "23": "Horario ampliado vespertino",
        "65": "Alojamiento",
        "97": "Comedor"
    },
    "actividades_extraescolares": {
        "24": "natación",
        "25": "futbol",
        "26": "ajedrez",
        "27": "otros deportes",
        "28": "violín",
        "29": "piano",
        "30": "ballet",
        "44": "tenis",
        "45": "otros instrumentos musicales",
        "60": "patinaje",
        "61": "robótica",
        "70": "gimnasia rítmica",
        "79": "cocina",
        "87": "danza española",
        "94": "hípica",
        "100": "teatro",
        "101": "danza",
        "126": "arte dramático",
        "139": "coro musical"
    },
    "menu_especial": {
        "31": "sin gluten",
        "32": "sin lactosa",
        "33": "vegetariano",
        "34": "para diabéticos",
        "66": "bajo en grasas",
        "98": "Halal",
        "102": "musulmán",
        "132": "vegano",
        "133": "hipercalórico (suplemento en calorías)"
    },
    "servicios_especiales": {
        "35": "Psicología infantil",
        "36": "Logopeda"
    },
    "programas_de_integracion": {
        "37": "Programa de prevención de acoso escolar (Cero Bullying)",
        "38": "Programa de integración social",
        "39": "Programa de igualdad"
    }
}